Metadata-Version: 1.1
Name: Julianexampleproject
Version: 0.0.1
Summary: A very basic calculator
Home-page: UNKNOWN
Author: Julian Reisch
Author-email: UNKNOWN
License: MIT
Keywords: calculator
Platform: UNKNOWN
Classifier: Development Status :: 5 - Production/Stable
Classifier: Intended Audience :: Education
Classifier: Operating System :: Microsoft :: Windows :: Windows 10
Classifier: License :: OSI Approved :: MIT License
Classifier: Programming Language :: Python :: 3
